leonardoWrapper/__init__.py
leonardoWrapper/leonardo.py
leonardowrapper-1.1.3.dist-info/licenses/LICENSE
leonardowrapper-1.1.3.dist-info/METADATA
leonardowrapper-1.1.3.dist-info/WHEEL
leonardowrapper-1.1.3.dist-info/top_level.txt
leonardowrapper-1.1.3.dist-info/RECORD
