Metadata-Version: 2.4
Name: leonardoWrapper
Version: 1.1.3
Summary: A wrapper for the leonardo.ai image generation
Home-page: https://github.com/theunkowndude/leonardoWrapper
Author: the_unkown_dude, anditv21
Author-email: zaima_max@proton.me
Requires-Python: >=3.6
License-File: LICENSE
Requires-Dist: tls-client
Dynamic: author
Dynamic: author-email
Dynamic: description
Dynamic: description-content-type
Dynamic: home-page
Dynamic: license-file
Dynamic: requires-dist
Dynamic: requires-python
Dynamic: summary
